inputselect/__init__.py
inputselect/main.py
inputselect-1.0.dist-info/METADATA
inputselect-1.0.dist-info/WHEEL
inputselect-1.0.dist-info/top_level.txt
inputselect-1.0.dist-info/RECORD
